mkdocs_video/__init__.py
mkdocs_video/plugin.py
m_mkdocs_video.test-0.0.1.dist-info/LICENSE
m_mkdocs_video.test-0.0.1.dist-info/METADATA
m_mkdocs_video.test-0.0.1.dist-info/WHEEL
m_mkdocs_video.test-0.0.1.dist-info/entry_points.txt
m_mkdocs_video.test-0.0.1.dist-info/top_level.txt
m_mkdocs_video.test-0.0.1.dist-info/RECORD
