Metadata-Version: 2.1
Name: m-mkdocs-video.test
Version: 0.0.1
Summary: Libs check filetype
Home-page: UNKNOWN
Author: MOBIO
Author-email: contact@mobio.vn
License: UNKNOWN
Platform: UNKNOWN
Classifier: Programming Language :: Python
Classifier: Programming Language :: Python :: 3.8
Classifier: Programming Language :: Python :: 3.9
License-File: LICENSE
